agora/__init__.py
agora/_modidx.py
agora/client.py
agora/config.py
agora/crypto.py
agora_python-0.0.8.dist-info/LICENSE
agora_python-0.0.8.dist-info/METADATA
agora_python-0.0.8.dist-info/WHEEL
agora_python-0.0.8.dist-info/entry_points.txt
agora_python-0.0.8.dist-info/top_level.txt
agora_python-0.0.8.dist-info/RECORD
