Metadata-Version: 2.1
Name: agora-python
Version: 0.0.8
Summary: Agora Python SDK to interact with Fewsats+Agora backend
Home-page: https://github.com/Fewsats/agora-python
Author: Fewsats
Author-email: pol@fewsats.com
License: Apache Software License 2.0
Keywords: nbdev jupyter notebook python
Classifier: Development Status :: 4 - Beta
Classifier: Intended Audience :: Developers
Classifier: Natural Language :: English
Classifier: Programming Language :: Python :: 3.7
Classifier: Programming Language :: Python :: 3.8
Classifier: Programming Language :: Python :: 3.9
Classifier: Programming Language :: Python :: 3.10
Classifier: Programming Language :: Python :: 3.11
Classifier: Programming Language :: Python :: 3.12
Classifier: License :: OSI Approved :: Apache Software License
Requires-Python: >=3.7
License-File: LICENSE
Requires-Dist: fastcore
Requires-Dist: httpx
Requires-Dist: cryptography
Provides-Extra: dev
